aanalyticsseg/__init__.py
aanalyticsseg/__version__.py
aanalyticsseg/actCreateSeg.py
aanalyticsseg/actCreateSegment.py
aanalyticsseg/actGetSeg.py
aanalyticsseg/actLibrarySeg.py
aanalyticsseg/actSegmentLibrary.py
aanalyticsseg/actSegmentSaver.py
aanalyticsseg/actUpdateSeg.py
aanalyticsseg/actUpdateSegment.py
aanalytcsseg-0.0.1.dist-info/METADATA
aanalytcsseg-0.0.1.dist-info/WHEEL
aanalytcsseg-0.0.1.dist-info/top_level.txt
aanalytcsseg-0.0.1.dist-info/RECORD
