Metadata-Version: 2.1
Name: aanalytcsseg
Version: 0.0.1
Summary: Automation tool for Team ACT
Home-page: https://github.com/SunkyeongLee/aanalyticsseg
Author: Sunkyeong Lee
Author-email: sunkyeong.lee@concentrix.com
License: UNKNOWN
Platform: UNKNOWN
Classifier: Programming Language :: Python :: 3
Classifier: License :: OSI Approved :: MIT License
Classifier: Operating System :: OS Independent
Requires-Python: >=3.6
